ipython_namespaces/__init__.py
ipython_namespaces/namespaces.py
ipython_namespaces-0.1.3.dist-info/WHEEL
ipython_namespaces-0.1.3.dist-info/METADATA
ipython_namespaces-0.1.3.dist-info/RECORD
